AUTHORS
HISTORY
LICENSE
MANIFEST.in
README.md
setup.cfg
setup.py
silex/__init__.py
silex/core.py
silex.egg-info/PKG-INFO
silex.egg-info/SOURCES.txt
silex.egg-info/dependency_links.txt
silex.egg-info/not-zip-safe
silex.egg-info/top_level.txt
tests/__init__.py