Metadata-Version: 1.1
Name: silex
Version: 0.2.0
Summary: string utilities
Home-page: https://github.com/walidsa3d/silex
Author: Walid Saad
Author-email: walid.sa3d@gmail.com
License: MIT
Platform: UNKNOWN
Classifier: Development Status :: 4 - Beta
Classifier: Intended Audience :: Developers
Classifier: License :: OSI Approved :: MIT License
Classifier: Operating System :: POSIX
Classifier: Operating System :: MacOS
Classifier: Operating System :: Unix
Classifier: Programming Language :: Python
Classifier: Topic :: Software Development :: Libraries :: Python Modules
